interpolate.py
setup.py
interpolate.egg-info/PKG-INFO
interpolate.egg-info/SOURCES.txt
interpolate.egg-info/dependency_links.txt
interpolate.egg-info/top_level.txt
interpolate.egg-info/zip-safe