Metadata-Version: 1.0
Name: interpolate
Version: 0.5.1
Summary: string interpolation
Home-page: http://edk141.co.uk/a/interpolate
Author: Ed Kellett
Author-email: edk141@gmail.com
License: MIT
Platform: UNKNOWN
Classifier: Development Status :: 4 - Beta
Classifier: License :: OSI Approved :: MIT License
Classifier: Operating System :: OS Independent
Classifier: Programming Language :: Python
